tubby/__init__.py
tubby/__main__.py
tubby/analyze.py
tubby/backup.py
tubby/download.py
tubby/file.py
tubby/info.py
tubby/manage.py
tubby/meta.py
tubby/query.py
tubby/reset.py
tubby/utils.py
tubby/data/logo.txt
tubby-1.0.3.dist-info/LICENSE
tubby-1.0.3.dist-info/METADATA
tubby-1.0.3.dist-info/WHEEL
tubby-1.0.3.dist-info/entry_points.txt
tubby-1.0.3.dist-info/top_level.txt
tubby-1.0.3.dist-info/RECORD
