Metadata-Version: 2.1
Name: tubby
Version: 1.0.3
Summary: A utility for the Genshin Impact Housing system
Home-page: https://github.com/kelvindecosta/tubby
Author: Kelvin DeCosta
Author-email: decostakelvin@gmail.com
License: MIT
Platform: UNKNOWN
Classifier: Programming Language :: Python :: 3
Classifier: Operating System :: Unix
Classifier: License :: OSI Approved :: MIT License
Classifier: Development Status :: 5 - Production/Stable
Classifier: Topic :: Games/Entertainment :: Role-Playing
Classifier: Topic :: Terminals
Classifier: Topic :: Utilities
Requires-Python: >=3.9
License-File: LICENSE
Requires-Dist: click
Requires-Dist: bs4
Requires-Dist: httpx
Requires-Dist: simple-term-menu
Requires-Dist: sty
Requires-Dist: tqdm
